MANIFEST.in
README
setup.py
sphinxcontrib/__init__.py
sphinxcontrib/taglist.css
sphinxcontrib/taglist.py
sphinxcontrib_taglist.egg-info/PKG-INFO
sphinxcontrib_taglist.egg-info/SOURCES.txt
sphinxcontrib_taglist.egg-info/dependency_links.txt
sphinxcontrib_taglist.egg-info/namespace_packages.txt
sphinxcontrib_taglist.egg-info/not-zip-safe
sphinxcontrib_taglist.egg-info/requires.txt
sphinxcontrib_taglist.egg-info/top_level.txt