Metadata-Version: 1.1
Name: sphinxcontrib-taglist
Version: 0.2
Summary: Sphinx "taglist" extension
Home-page: http://github.com/spinus/sphinxcontrib-taglist
Author: Tomek Czyż
Author-email: tomekczyz@gmail.com
License: BSD
Download-URL: http://pypi.python.org/pypi/sphinxcontrib-taglist
Platform: any
Classifier: Development Status :: 4 - Beta
Classifier: Environment :: Console
Classifier: Environment :: Web Environment
Classifier: Intended Audience :: Developers
Classifier: License :: OSI Approved :: BSD License
Classifier: Operating System :: OS Independent
Classifier: Programming Language :: Python
Classifier: Topic :: Documentation
